{
    "os": "Windows-10-10.0.19044-SP0",
    "python": "3.9.13",
    "heartbeatAt": "2022-11-26T09:46:54.394185",
    "startedAt": "2022-11-26T09:46:53.652435",
    "docker": null,
    "cuda": null,
    "args": [],
    "state": "running",
    "program": "C:\\Users\\alex2\\Desktop\\SystemsOptimization\\main.py",
    "codePath": "main.py",
    "git": {
        "remote": "https://github.com/alessandro-canevaro/SystemsOptimization.git",
        "commit": "51edb0d6faad7edb7ee5c3d16ca31cad7ed04143"
    },
    "email": "alessandrocanevaro26@gmail.com",
    "root": "C:/Users/alex2/Desktop/SystemsOptimization",
    "host": "ALE-ROG",
    "username": "alex2",
    "executable": "C:\\Users\\alex2\\Desktop\\SystemsOptimization\\so_venv\\Scripts\\python.exe",
    "cpu_count": 4,
    "cpu_count_logical": 8,
    "cpu_freq": {
        "current": 3501.0,
        "min": 0.0,
        "max": 3501.0
    },
    "cpu_freq_per_core": [
        {
            "current": 3501.0,
            "min": 0.0,
            "max": 3501.0
        }
    ],
    "disk": {
        "total": 118.62993240356445,
        "used": 54.560733795166016
    },
    "gpu": "GeForce GTX 770",
    "gpu_count": 1,
    "gpu_devices": [
        {
            "name": "GeForce GTX 770",
            "memory_total": 2147483648
        }
    ],
    "memory": {
        "total": 15.93829345703125
    }
}
